openqaoa/__init__.py
openqaoa/_version.py
openqaoa/utilities.py
openqaoa/algorithms/__init__.py
openqaoa/algorithms/baseworkflow.py
openqaoa/algorithms/workflow_properties.py
openqaoa/algorithms/qaoa/__init__.py
openqaoa/algorithms/qaoa/qaoa_benchmark.py
openqaoa/algorithms/qaoa/qaoa_result.py
openqaoa/algorithms/qaoa/qaoa_workflow.py
openqaoa/algorithms/rqaoa/__init__.py
openqaoa/algorithms/rqaoa/rqaoa_result.py
openqaoa/algorithms/rqaoa/rqaoa_utils.py
openqaoa/algorithms/rqaoa/rqaoa_workflow.py
openqaoa/algorithms/rqaoa/rqaoa_workflow_properties.py
openqaoa/backends/__init__.py
openqaoa/backends/basebackend.py
openqaoa/backends/basedevice.py
openqaoa/backends/cost_function.py
openqaoa/backends/devices_core.py
openqaoa/backends/gates_vectorized.py
openqaoa/backends/plugin_finder.py
openqaoa/backends/qaoa_analytical_sim.py
openqaoa/backends/qaoa_backend.py
openqaoa/backends/qaoa_device.py
openqaoa/backends/qaoa_vectorized.py
openqaoa/backends/wrapper.py
openqaoa/derivatives/__init__.py
openqaoa/derivatives/derivative_functions.py
openqaoa/derivatives/qfim.py
openqaoa/optimizers/__init__.py
openqaoa/optimizers/logger_vqa.py
openqaoa/optimizers/qaoa_optimizer.py
openqaoa/optimizers/training_vqa.py
openqaoa/optimizers/optimization_methods/CANS.py
openqaoa/optimizers/optimization_methods/SPSA.py
openqaoa/optimizers/optimization_methods/__init__.py
openqaoa/optimizers/optimization_methods/grad_descent.py
openqaoa/optimizers/optimization_methods/iCANS.py
openqaoa/optimizers/optimization_methods/natural_grad_descent.py
openqaoa/optimizers/optimization_methods/newton_descent.py
openqaoa/optimizers/optimization_methods/rmsprop.py
openqaoa/optimizers/optimization_methods/stochastic_grad_descent.py
openqaoa/optimizers/pennylane/__init__.py
openqaoa/optimizers/pennylane/optimization_methods_pennylane.py
openqaoa/optimizers/pennylane/fourier/__init__.py
openqaoa/optimizers/pennylane/fourier/reconstruct.py
openqaoa/optimizers/pennylane/math/__init__.py
openqaoa_core-0.2.6.dist-info/LICENSE
openqaoa_core-0.2.6.dist-info/METADATA
openqaoa_core-0.2.6.dist-info/WHEEL
openqaoa_core-0.2.6.dist-info/top_level.txt
openqaoa_core-0.2.6.dist-info/RECORD
