Metadata-Version: 2.1
Name: openqaoa-core
Version: 0.2.6
Summary: OpenQAOA is a python open-source multi-backend Software Development Kit to create, customise and execute the Quantum Approximate Optimisation Algorithm (QAOA) on Noisy Intermediate-Scale Quantum (NISQ) devices, and simulators
Home-page: https://github.com/entropicalabs/openqaoa
Author: Entropica Labs
License: MIT
Keywords: quantum optimisation SDK
Classifier: Programming Language :: Python :: 3.8
Classifier: Programming Language :: Python :: 3.9
Classifier: Programming Language :: Python :: 3.10
Classifier: Operating System :: OS Independent
Requires-Python: >=3.8, <3.11
License-File: LICENSE
Requires-Dist: pandas >=1.3.5
Requires-Dist: sympy >=1.10.1
Requires-Dist: numpy <2.0,>=1.22.3
Requires-Dist: networkx >=2.8
Requires-Dist: matplotlib >=3.4.3
Requires-Dist: scipy >=1.8
Requires-Dist: docplex ==2.25.236
Requires-Dist: autograd >=1.4
Requires-Dist: semantic-version >=2.10
Requires-Dist: autoray >=0.3.1
Requires-Dist: requests
Requires-Dist: ipython >=8.2.0
Requires-Dist: mitiq
Provides-Extra: all
Requires-Dist: sphinx >=4.5.0 ; extra == 'all'
Requires-Dist: sphinx-autodoc-typehints >=1.18.1 ; extra == 'all'
Requires-Dist: sphinx-rtd-theme >=1.0.0 ; extra == 'all'
Requires-Dist: nbsphinx >=0.8.9 ; extra == 'all'
Requires-Dist: ipython >=8.10.0 ; extra == 'all'
Requires-Dist: nbconvert >=6.5.1 ; extra == 'all'
Requires-Dist: myst-parser >=2.0.0 ; extra == 'all'
Requires-Dist: pytest >=7.1.0 ; extra == 'all'
Requires-Dist: pytest-xdist ; extra == 'all'
Requires-Dist: pytest-cov >=3.0.0 ; extra == 'all'
Requires-Dist: pandas >=1.4.3 ; extra == 'all'
Requires-Dist: plotly >=5.9.0 ; extra == 'all'
Requires-Dist: cplex >=22.1.1 ; extra == 'all'
Provides-Extra: docs
Requires-Dist: sphinx >=4.5.0 ; extra == 'docs'
Requires-Dist: sphinx-autodoc-typehints >=1.18.1 ; extra == 'docs'
Requires-Dist: sphinx-rtd-theme >=1.0.0 ; extra == 'docs'
Requires-Dist: nbsphinx >=0.8.9 ; extra == 'docs'
Requires-Dist: ipython >=8.10.0 ; extra == 'docs'
Requires-Dist: nbconvert >=6.5.1 ; extra == 'docs'
Requires-Dist: myst-parser >=2.0.0 ; extra == 'docs'
Provides-Extra: tests
Requires-Dist: pytest >=7.1.0 ; extra == 'tests'
Requires-Dist: pytest-xdist ; extra == 'tests'
Requires-Dist: pytest-cov >=3.0.0 ; extra == 'tests'
Requires-Dist: nbconvert >=6.5.1 ; extra == 'tests'
Requires-Dist: pandas >=1.4.3 ; extra == 'tests'
Requires-Dist: plotly >=5.9.0 ; extra == 'tests'
Provides-Extra: tests-cplex
Requires-Dist: pytest >=7.1.0 ; extra == 'tests-cplex'
Requires-Dist: pytest-xdist ; extra == 'tests-cplex'
Requires-Dist: pytest-cov >=3.0.0 ; extra == 'tests-cplex'
Requires-Dist: nbconvert >=6.5.1 ; extra == 'tests-cplex'
Requires-Dist: pandas >=1.4.3 ; extra == 'tests-cplex'
Requires-Dist: plotly >=5.9.0 ; extra == 'tests-cplex'
Requires-Dist: cplex >=22.1.1 ; extra == 'tests-cplex'
